brasil.gov.portlets-1.0rc2-py2.7-nspkg.pth
brasil/gov/portlets/__init__.py
brasil/gov/portlets/config.py
brasil/gov/portlets/configure.zcml
brasil/gov/portlets/i18n.sh
brasil/gov/portlets/interfaces.py
brasil/gov/portlets/patches.py
brasil/gov/portlets/profiles.zcml
brasil/gov/portlets/testing.py
brasil/gov/portlets/vocabulary.py
brasil/gov/portlets/locales/brasil.gov.portlets-manual.pot
brasil/gov/portlets/locales/brasil.gov.portlets.pot
brasil/gov/portlets/locales/plone.pot
brasil/gov/portlets/locales/pt_BR/LC_MESSAGES/brasil.gov.portlets.po
brasil/gov/portlets/locales/pt_BR/LC_MESSAGES/plone.po
brasil/gov/portlets/portlets/__init__.py
brasil/gov/portlets/portlets/audio.py
brasil/gov/portlets/portlets/audiogallery.py
brasil/gov/portlets/portlets/collection.py
brasil/gov/portlets/portlets/configure.zcml
brasil/gov/portlets/portlets/mediacarousel.py
brasil/gov/portlets/portlets/video.py
brasil/gov/portlets/portlets/videogallery.py
brasil/gov/portlets/portlets/templates/audio.pt
brasil/gov/portlets/portlets/templates/audiogallery.pt
brasil/gov/portlets/portlets/templates/collection.pt
brasil/gov/portlets/portlets/templates/mediacarousel.pt
brasil/gov/portlets/portlets/templates/video.pt
brasil/gov/portlets/portlets/templates/videogallery.pt
brasil/gov/portlets/profiles/default/brasil.gov.portlets.txt
brasil/gov/portlets/profiles/default/browserlayer.xml
brasil/gov/portlets/profiles/default/cssregistry.xml
brasil/gov/portlets/profiles/default/jsregistry.xml
brasil/gov/portlets/profiles/default/metadata.xml
brasil/gov/portlets/profiles/default/portlets.xml
brasil/gov/portlets/profiles/testfixture/metadata.xml
brasil/gov/portlets/profiles/testfixture/propertiestool.xml
brasil/gov/portlets/profiles/testfixture/types.xml
brasil/gov/portlets/profiles/testfixture/types/Audio.xml
brasil/gov/portlets/profiles/testfixture/types/MPEG_Audio_File.xml
brasil/gov/portlets/profiles/testfixture/types/OGG_Audio_File.xml
brasil.gov.portlets-1.0rc2.dist-info/DESCRIPTION.rst
brasil.gov.portlets-1.0rc2.dist-info/METADATA
brasil.gov.portlets-1.0rc2.dist-info/RECORD
brasil.gov.portlets-1.0rc2.dist-info/WHEEL
brasil.gov.portlets-1.0rc2.dist-info/entry_points.txt
brasil.gov.portlets-1.0rc2.dist-info/metadata.json
brasil.gov.portlets-1.0rc2.dist-info/namespace_packages.txt
brasil.gov.portlets-1.0rc2.dist-info/top_level.txt
