Metadata-Version: 2.0
Name: brasil.gov.portlets
Version: 1.0rc2
Summary: Portlets para Portal PadrÄĹo
Home-page: https://github.com/plonegovbr/brasil.gov.portlets
Author: PloneGovBr
Author-email: gov@plone.org.br
License: GPLv2
Keywords: plonegovbr portlets brasil plone
Platform: UNKNOWN
Classifier: Development Status :: 4 - Beta
Classifier: Environment :: Web Environment
Classifier: Framework :: Plone
Classifier: Framework :: Plone :: 4.3
Classifier: Intended Audience :: System Administrators
Classifier: License :: OSI Approved :: GNU General Public License v2 (GPLv2)
Classifier: Operating System :: OS Independent
Classifier: Programming Language :: Python
Classifier: Programming Language :: Python :: 2.7
Classifier: Topic :: Software Development :: Libraries :: Python Modules
Requires-Dist: Products.CMFPlone (>=4.3)
Requires-Dist: Products.CMFQuickInstallerTool
Requires-Dist: Products.GenericSetup
Requires-Dist: brasil.gov.portal
Requires-Dist: brasil.gov.tiles
Requires-Dist: five.pt
Requires-Dist: lxml
Requires-Dist: plone.api
Requires-Dist: plone.app.dexterity
Requires-Dist: plone.app.portlets
Requires-Dist: plone.app.upgrade
Requires-Dist: plone.memoize
Requires-Dist: plone.portlets
Requires-Dist: sc.embedder
Requires-Dist: setuptools
Requires-Dist: zope.component
Requires-Dist: zope.i18nmessageid
Requires-Dist: zope.interface
Requires-Dist: zope.schema
Provides-Extra: test
Requires-Dist: plone.app.contenttypes (<1.1a1); extra == 'test'
Requires-Dist: plone.app.robotframework; extra == 'test'
Requires-Dist: plone.app.testing[robot] (>=4.2.2); extra == 'test'
Requires-Dist: plone.browserlayer; extra == 'test'
Requires-Dist: plone.namedfile; extra == 'test'
Requires-Dist: plone.testing; extra == 'test'
Requires-Dist: robotsuite; extra == 'test'
